LICENSE
README.md
setup.py
graphtype/__init__.py
graphtype.egg-info/PKG-INFO
graphtype.egg-info/SOURCES.txt
graphtype.egg-info/dependency_links.txt
graphtype.egg-info/top_level.txt
tests/__init__.py
tests/test_classes.py
tests/test_edgedata.py
tests/test_nodedata.py
tests/test_validate.py