Metadata-Version: 2.1
Name: graphtype
Version: 0.1.0
Summary: Enforce graph, node and edge attribute types on NetworkX Graphs.
Home-page: https://github.com/a-r-j/graphtype
Author: Arian Jamasb
Author-email: arian@jamasb.io
License: UNKNOWN
Platform: UNKNOWN
Classifier: Programming Language :: Python :: 3
Classifier: Operating System :: OS Independent
Classifier: License :: OSI Approved :: Apache Software License
License-File: LICENSE
